physics_utils/__init__.py
physics_utils/data.py
physics_utils/graph.py
physics_utils/table.py
physics_utils/data/__init__.py
physics_utils/data/math.py
physics_utils/data/md_base.py
physics_utils/data/md_steps.py
physics_utils/data/measureddata.py
physics_utils/data/util.py
physics_utils/script/__main__.py
physics_utils/script/block.py
physics_utils/script/builtin.py
physics_utils/script/control.py
physics_utils/script/datatypes.py
physics_utils/script/environment.py
physics_utils/script/expressions.py
physics_utils/script/main.py
physics_utils/script/statements.py
physics_utils/script/util.py
physics_utils/script/visitor_interpreter.py
physics_utils/script/antlr_build/ExprLexer.py
physics_utils/script/antlr_build/ExprListener.py
physics_utils/script/antlr_build/ExprParser.py
physics_utils/script/antlr_build/ExprVisitor.py
physics_utils-0.3.2.dist-info/licenses/LICENSE
physics_utils-0.3.2.dist-info/METADATA
physics_utils-0.3.2.dist-info/WHEEL
physics_utils-0.3.2.dist-info/top_level.txt
physics_utils-0.3.2.dist-info/RECORD
