Metadata-Version: 2.4
Name: physics-utils
Version: 0.3.2
Summary: Helpers for empirical data handling and plotting
Author-email: Jahan Rashidi <hiimjahan@gmail.com>
License-Expression: GPL-3.0-only
Project-URL: Homepage, https://github.com/ImNotJahan/PhysicsTools
Project-URL: Source, https://github.com/ImNotJahan/PhysicsTools
Project-URL: Issues, https://github.com/ImNotJahan/PhysicsTools/issues
Project-URL: Documentation, https://physics-utils.readthedocs.io
Classifier: Programming Language :: Python :: 3
Classifier: Operating System :: OS Independent
Requires-Python: >=3.11
License-File: LICENSE
Requires-Dist: numpy~=2.3.1
Requires-Dist: matplotlib~=3.10.6
Requires-Dist: scipy~=1.16.2
Requires-Dist: pandas~=2.3.2
Requires-Dist: antlr4-python3-runtime~=4.13.0
Dynamic: license-file
